aiko/__init__.py
aiko/kernel.py
aiko/message_box.py
aiko/process.py
aiko_kernel-1.0.1.dist-info/LICENSE
aiko_kernel-1.0.1.dist-info/METADATA
aiko_kernel-1.0.1.dist-info/WHEEL
aiko_kernel-1.0.1.dist-info/top_level.txt
aiko_kernel-1.0.1.dist-info/RECORD
